certbot/__init__.py
certbot/achallenges.py
certbot/crypto_util.py
certbot/errors.py
certbot/interfaces.py
certbot/main.py
certbot/ocsp.py
certbot/reverter.py
certbot/ssl-dhparams.pem
certbot/util.py
certbot/_internal/__init__.py
certbot/_internal/account.py
certbot/_internal/auth_handler.py
certbot/_internal/cert_manager.py
certbot/_internal/client.py
certbot/_internal/configuration.py
certbot/_internal/constants.py
certbot/_internal/eff.py
certbot/_internal/error_handler.py
certbot/_internal/hooks.py
certbot/_internal/lock.py
certbot/_internal/log.py
certbot/_internal/main.py
certbot/_internal/renewal.py
certbot/_internal/reporter.py
certbot/_internal/storage.py
certbot/_internal/updater.py
certbot/_internal/cli/__init__.py
certbot/_internal/cli/cli_constants.py
certbot/_internal/cli/cli_utils.py
certbot/_internal/cli/group_adder.py
certbot/_internal/cli/helpful.py
certbot/_internal/cli/paths_parser.py
certbot/_internal/cli/plugins_parsing.py
certbot/_internal/cli/report_config_interaction.py
certbot/_internal/cli/subparsers.py
certbot/_internal/cli/verb_help.py
certbot/_internal/display/__init__.py
certbot/_internal/display/completer.py
certbot/_internal/display/dummy_readline.py
certbot/_internal/plugins/__init__.py
certbot/_internal/plugins/disco.py
certbot/_internal/plugins/manual.py
certbot/_internal/plugins/null.py
certbot/_internal/plugins/selection.py
certbot/_internal/plugins/standalone.py
certbot/_internal/plugins/webroot.py
certbot/compat/__init__.py
certbot/compat/_path.py
certbot/compat/filesystem.py
certbot/compat/misc.py
certbot/compat/os.py
certbot/display/__init__.py
certbot/display/ops.py
certbot/display/util.py
certbot/plugins/__init__.py
certbot/plugins/common.py
certbot/plugins/dns_common.py
certbot/plugins/dns_common_lexicon.py
certbot/plugins/dns_test_common.py
certbot/plugins/dns_test_common_lexicon.py
certbot/plugins/enhancements.py
certbot/plugins/storage.py
certbot/plugins/util.py
certbot/tests/__init__.py
certbot/tests/acme_util.py
certbot_zerossl-1.7.0.dev0.dist-info/LICENSE.txt
certbot_zerossl-1.7.0.dev0.dist-info/METADATA
certbot_zerossl-1.7.0.dev0.dist-info/WHEEL
certbot_zerossl-1.7.0.dev0.dist-info/entry_points.txt
certbot_zerossl-1.7.0.dev0.dist-info/top_level.txt
certbot_zerossl-1.7.0.dev0.dist-info/RECORD
