Metadata-Version: 2.1
Name: certbot-zerossl
Version: 1.7.0.dev0
Summary: ACME client (with zerossl extensions)
Home-page: https://zerossl.com
Author: ZeroSSL
Author-email: christoph.witzany@apilayer.com
License: Apache License 2.0
Platform: UNKNOWN
Classifier: Development Status :: 5 - Production/Stable
Classifier: Environment :: Console
Classifier: Environment :: Console :: Curses
Classifier: Intended Audience :: System Administrators
Classifier: License :: OSI Approved :: Apache Software License
Classifier: Operating System :: POSIX :: Linux
Classifier: Programming Language :: Python
Classifier: Programming Language :: Python :: 2
Classifier: Programming Language :: Python :: 2.7
Classifier: Programming Language :: Python :: 3
Classifier: Programming Language :: Python :: 3.5
Classifier: Programming Language :: Python :: 3.6
Classifier: Programming Language :: Python :: 3.7
Classifier: Programming Language :: Python :: 3.8
Classifier: Topic :: Internet :: WWW/HTTP
Classifier: Topic :: Security
Classifier: Topic :: System :: Installation/Setup
Classifier: Topic :: System :: Networking
Classifier: Topic :: System :: Systems Administration
Classifier: Topic :: Utilities
Requires-Python: >=2.7, !=3.0.*, !=3.1.*, !=3.2.*, !=3.3.*, !=3.4.*
Requires-Dist: acme (>=1.6.0)
Requires-Dist: ConfigArgParse (>=0.9.3)
Requires-Dist: configobj
Requires-Dist: cryptography (>=1.2.3)
Requires-Dist: distro (>=1.0.1)
Requires-Dist: josepy (>=1.1.0)
Requires-Dist: parsedatetime (>=1.3)
Requires-Dist: pyrfc3339
Requires-Dist: pytz
Requires-Dist: setuptools
Requires-Dist: zope.component
Requires-Dist: zope.interface
Requires-Dist: mock ; python_version < "3.3"
Requires-Dist: pywin32 (>=227) ; sys_platform == "win32"
Provides-Extra: dev
Requires-Dist: coverage ; extra == 'dev'
Requires-Dist: pytest ; extra == 'dev'
Requires-Dist: pytest-cov ; extra == 'dev'
Requires-Dist: pytest-xdist ; extra == 'dev'
Requires-Dist: tox ; extra == 'dev'
Requires-Dist: twine ; extra == 'dev'
Requires-Dist: wheel ; extra == 'dev'
Provides-Extra: dev3
Requires-Dist: astroid ; extra == 'dev3'
Requires-Dist: ipdb ; extra == 'dev3'
Requires-Dist: mypy ; extra == 'dev3'
Requires-Dist: pylint ; extra == 'dev3'
Provides-Extra: docs
Requires-Dist: repoze.sphinx.autointerface ; extra == 'docs'
Requires-Dist: Sphinx (>=1.2) ; extra == 'docs'
Requires-Dist: sphinx-rtd-theme ; extra == 'docs'
